odoo/addons/sale_order_country_allowed_product/README.rst
odoo/addons/sale_order_country_allowed_product/__init__.py
odoo/addons/sale_order_country_allowed_product/__manifest__.py
odoo/addons/sale_order_country_allowed_product/i18n/sale_order_country_allowed_product.pot
odoo/addons/sale_order_country_allowed_product/models/__init__.py
odoo/addons/sale_order_country_allowed_product/models/product_product.py
odoo/addons/sale_order_country_allowed_product/models/product_template.py
odoo/addons/sale_order_country_allowed_product/models/sale_order.py
odoo/addons/sale_order_country_allowed_product/models/sale_order_line.py
odoo/addons/sale_order_country_allowed_product/readme/CONFIGURE.rst
odoo/addons/sale_order_country_allowed_product/readme/CONTRIBUTORS.rst
odoo/addons/sale_order_country_allowed_product/readme/DESCRIPTION.rst
odoo/addons/sale_order_country_allowed_product/readme/USAGE.rst
odoo/addons/sale_order_country_allowed_product/security/res_groups.xml
odoo/addons/sale_order_country_allowed_product/static/description/icon.png
odoo/addons/sale_order_country_allowed_product/static/description/index.html
odoo/addons/sale_order_country_allowed_product/tests/__init__.py
odoo/addons/sale_order_country_allowed_product/tests/test_sale_order_country_allowed_product.py
odoo/addons/sale_order_country_allowed_product/views/product_views.xml
odoo/addons/sale_order_country_allowed_product/views/sale_order_views.xml
odoo_addon_sale_order_country_allowed_product-16.0.1.0.0.2.dist-info/METADATA
odoo_addon_sale_order_country_allowed_product-16.0.1.0.0.2.dist-info/WHEEL
odoo_addon_sale_order_country_allowed_product-16.0.1.0.0.2.dist-info/top_level.txt
odoo_addon_sale_order_country_allowed_product-16.0.1.0.0.2.dist-info/RECORD
